{
  "$schema": "https://schemas.wp.org/trunk/block.json",
  "apiVersion": 2,
  "name": "post-grid/content-slider",
  "title": "Content Slider",
  "textdomain": "post-grid",
  "category": "post-grid",
  "usesContext": [
    "postId",
    "loopIndex",
    "postType",
    "queryId"
  ],
  "supports": {
    "align": [
      "wide",
      "full"
    ]
  },
  "attributes": {
    "wrapper": {
      "type": "object",
      "default": {
        "options": {
          "class": "pg-content-slider"
        },
        "styles": {
          "backgroundColor": {
            "Desktop": "#f1f7f9"
          }
        }
      }
    },
    "navsWrap": {
      "type": "object",
      "default": {
        "options": {
          "class": "nav-wrap"
        },
        "styles": {
          "display": {
            "Desktop": "flex"
          },
          "width": {
            "Desktop": "100%"
          },
          "justifyContent": {
            "Desktop": "space-between"
          },
          "alignItems": {
            "Desktop": "center"
          },
          "position": {
            "Desktop": "absolute !important"
          },
          "top": {
            "Desktop": "50%"
          },
          "transform": {
            "Desktop": "translateY(-50%)"
          }
        }
      }
    },
    "perv": {
      "type": "object",
      "default": {
        "options": {
          "text": "Prev",
          "class": ""
        },
        "styles": {
          "fontSize": {
            "Desktop": "18px"
          },
          "fontFamily": {
            "Desktop": "Poppins"
          },
          "fontStyle": {
            "Desktop": "normal"
          },
          "fontWeight": {
            "Desktop": "400"
          },
          "textAlign": {
            "Desktop": "left"
          },
          "color": {
            "Desktop": "#ffffff"
          },
          "backgroundColor": {
            "Desktop": "#1F2E45"
          },
          "borderRadius": {
            "Desktop": "50px"
          },
          "padding": {
            "Desktop": "5px 20px 5px 20px"
          }
        }
      }
    },
    "pervIcon": {
      "type": "object",
      "default": {
        "options": {
          "position": "before",
          "class": "",
          "library": "fontAwesome",
          "srcType": "class",
          "iconSrc": "fas fa-chevron-left"
        },
        "styles": {
          "padding": {
            "Desktop": "0px 10px 0px 0px"
          },
          "fontSize": {
            "Desktop": "16px"
          }
        }
      }
    },
    "next": {
      "type": "object",
      "default": {
        "options": {
          "text": "Next",
          "class": ""
        },
        "styles": {
          "fontSize": {
            "Desktop": "18px"
          },
          "fontFamily": {
            "Desktop": "Poppins"
          },
          "fontStyle": {
            "Desktop": "normal"
          },
          "fontWeight": {
            "Desktop": "400"
          },
          "textAlign": {
            "Desktop": "right"
          },
          "color": {
            "Desktop": "#ffffff"
          },
          "backgroundColor": {
            "Desktop": "#1F2E45"
          },
          "borderRadius": {
            "Desktop": "50px"
          },
          "padding": {
            "Desktop": "5px 20px 5px 20px"
          }
        }
      }
    },
    "nextIcon": {
      "type": "object",
      "default": {
        "options": {
          "position": "after",
          "class": "",
          "library": "fontAwesome",
          "srcType": "class",
          "iconSrc": "fas fa-chevron-right"
        },
        "styles": {
          "padding": {
            "Desktop": "0px 0px 0px 10px"
          },
          "fontSize": {
            "Desktop": "16px"
          }
        }
      }
    },
    "paginationWrap": {
      "type": "object",
      "default": {
        "options": {
          "tag": "ul",
          "class": ""
        },
        "styles": {
          "display": {
            "Desktop": "flex"
          },
          "justifyContent": {
            "Desktop": "center"
          },
          "gap": {
            "Desktop": "1em"
          }
        }
      }
    },
    "pagination": {
      "type": "object",
      "default": {
        "options": {
          "tag": "span",
          "class": ""
        },
        "styles": {
          "padding": {
            "Desktop": "15px 0px 15px 0px"
          },
          "border": {
            "Desktop": "2px solid #1f2e45"
          },
          "height": {
            "Desktop": "10px"
          },
          "width": {
            "Desktop": "10px"
          },
          "borderRadius": {
            "Desktop": "50%"
          }
        }
      }
    },
    "paginationActive": {
      "type": "object",
      "default": {
        "options": {
          "class": ""
        },
        "styles": {
          "backgroundColor": {
            "Desktop": "#1f2e45"
          }
        }
      }
    },
    "sliderOptions": {
      "type": "object",
      "default": {}
    },
    "sliderOptionsRes": {
      "type": "object",
      "default": {}
    },
    "blockId": {
      "type": "string",
      "default": ""
    },
    "blockCssY": {
      "type": "object",
      "default": {
        "items": {}
      }
    }
  },
  "editorStyle": "pgcontent-slider-splide-core",
  "script": "front_script",
  "keywords": [
    "Content slider",
    "Image slider",
    "Video slider",
    "Slider block",
    "Carousel block",
    "Carousel slider",
    "Custom content slider"
  ],
  "description": "Content slider is a powerful block to display content in a slider."
}